LICENSE
MANIFEST.in
README.rst
auth.cfg.sample
rules.cfg
setup.cfg
setup.py
gitbot/__init__.py
gitbot/__main__.py
gitbot/github_issues_bot.py
gitbot/web_listener.py
gitbot.egg-info/PKG-INFO
gitbot.egg-info/SOURCES.txt
gitbot.egg-info/dependency_links.txt
gitbot.egg-info/entry_points.txt
gitbot.egg-info/requires.txt
gitbot.egg-info/top_level.txt
gitbot/static/css/bootstrap-theme.css
gitbot/static/css/bootstrap-theme.min.css
gitbot/static/css/bootstrap.css
gitbot/static/css/bootstrap.min.css
gitbot/templates/about.html
tests/conftest.py
tests/test_fetch_issues.py
tests/test_issue_class.py
tests/test_process_issue.py
tests/test_rule_class.py
tests/test_web_listener.py
tests/fixtures/cassettes/nic.json
tests/fixtures/cassettes/test_fetch_issues.test_betamax.json
tests/fixtures/cassettes/test_fetch_issues.test_fetch_issues.json
tests/fixtures/cassettes/test_issue_class.test_parse_correct.json
tests/fixtures/cassettes/test_issue_class.test_parse_fail.json