Metadata-Version: 1.1
Name: gitbot
Version: 0.5
Summary: Automatically label GitHub issues based on regexp rules.
Home-page: https://github.com/melkamar/gitbot
Author: Martin Melka
Author-email: melkamar@fit.cvut.cz
License: MIT
Keywords: github,labeling,issues
Platform: UNKNOWN
Classifier: Development Status :: 4 - Beta
Classifier: Framework :: Flask
Classifier: Intended Audience :: Developers
Classifier: License :: OSI Approved :: MIT License
Classifier: Natural Language :: English
Classifier: Programming Language :: Python
Classifier: Programming Language :: Python :: 3
Classifier: Programming Language :: Python :: 3.5
Classifier: Topic :: Software Development
Classifier: Topic :: Software Development :: Bug Tracking
